LICENSE
README.md
setup.py
seedapi/__init__.py
seedapi/seed.py
seedapi.egg-info/PKG-INFO
seedapi.egg-info/SOURCES.txt
seedapi.egg-info/dependency_links.txt
seedapi.egg-info/requires.txt
seedapi.egg-info/top_level.txt