Metadata-Version: 2.1
Name: seedapi
Version: 0.0.3
Summary: Api library for Seed Platform
Author: imrc
Author-email: imrc@aiit.org.cn
Classifier: Programming Language :: Python :: 3
Classifier: License :: OSI Approved :: MIT License
Classifier: Operating System :: OS Independent
License-File: LICENSE
Requires-Dist: tqdm>=4.60
Requires-Dist: requests>=2.22
